[
    {
        "Nome": "Paradisco Produções",
        "Slogan": "Paradisco Produções Ltda",
        "Telefone 1": "(86) 99921-2284",
        "Telefone 2": "(86) 99921-2284",
        "E-mail": "paradiscoproducoes@gmail.com",
        "Site": "",
        "Facebook": "https://www.facebook.com/abrapeoficial/",
        "Instagram": "https://www.instagram.com/abrapeoficial"
    },
    {
        "Nome": "Blr Producoes",
        "Slogan": "Blr Producoes de Eventos Ltda",
        "Telefone 1": "(86) 3303-7601",
        "Telefone 2": "(86) 3303-7601",
        "E-mail": "contato@mundoblr.com.br",
        "Site": "",
        "Facebook": "https://www.facebook.com/abrapeoficial/",
        "Instagram": "https://www.instagram.com/abrapeoficial"
    },
    {
        "Nome": "Kalor Producoes",
        "Slogan": "Kalor Producoes Propaganda e Marketing Ltda",
        "Telefone 1": "(86) 2107-3000",
        "Telefone 2": "(86) 99402-6796",
        "E-mail": "tielreis@meionorte.com",
        "Site": "http://www.instagram.com/kalorproducoes",
        "Facebook": "https://www.facebook.com/abrapeoficial/",
        "Instagram": "https://www.instagram.com/abrapeoficial"
    }
]